[
  {
    "name": "tooltip",
    "type": "registry:ui",
    "dependencies": [
      "@radix-ui/react-tooltip"
    ],
    "files": [
      null
    ]
  },
  {
    "name": "toggle",
    "type": "registry:ui",
    "dependencies": [
      "@radix-ui/react-toggle",
      "class-variance-authority"
    ],
    "files": [
      null
    ]
  },
  {
    "name": "toggle-group",
    "type": "registry:ui",
    "dependencies": [
      "@radix-ui/react-toggle-group",
      "class-variance-authority"
    ],
    "files": [
      null
    ]
  },
  {
    "name": "textarea",
    "type": "registry:ui",
    "dependencies": [
      "none"
    ],
    "files": [
      null
    ]
  },
  {
    "name": "tabs",
    "type": "registry:ui",
    "dependencies": [
      "@radix-ui/react-tabs",
      "class-variance-authority"
    ],
    "files": [
      null
    ]
  },
  {
    "name": "table",
    "type": "registry:ui",
    "dependencies": [
      "none"
    ],
    "files": [
      null
    ]
  },
  {
    "name": "switch",
    "type": "registry:ui",
    "dependencies": [
      "@radix-ui/react-switch"
    ],
    "files": [
      null
    ]
  },
  {
    "name": "spinner",
    "type": "registry:ui",
    "dependencies": [
      "class-variance-authority",
      "lucide-react"
    ],
    "files": [
      null
    ]
  },
  {
    "name": "sonner",
    "type": "registry:ui",
    "dependencies": [
      "sonner",
      "next-themes"
    ],
    "files": [
      null
    ]
  },
  {
    "name": "slider",
    "type": "registry:ui",
    "dependencies": [
      "@radix-ui/react-slider"
    ],
    "files": [
      null
    ]
  },
  {
    "name": "skeleton",
    "type": "registry:ui",
    "dependencies": [
      "none"
    ],
    "files": [
      null
    ]
  },
  {
    "name": "sidebar",
    "type": "registry:ui",
    "dependencies": [
      "@radix-ui/react-slot",
      "class-variance-authority",
      "lucide-react"
    ],
    "files": [
      null
    ]
  },
  {
    "name": "sheet",
    "type": "registry:ui",
    "dependencies": [
      "@radix-ui/react-dialog",
      "class-variance-authority",
      "lucide-react"
    ],
    "files": [
      null
    ]
  },
  {
    "name": "separator",
    "type": "registry:ui",
    "dependencies": [
      "@radix-ui/react-separator"
    ],
    "files": [
      null
    ]
  },
  {
    "name": "select",
    "type": "registry:ui",
    "dependencies": [
      "@radix-ui/react-select",
      "lucide-react"
    ],
    "files": [
      null
    ]
  },
  {
    "name": "scroll-area",
    "type": "registry:ui",
    "dependencies": [
      "@radix-ui/react-scroll-area"
    ],
    "files": [
      null
    ]
  },
  {
    "name": "resizable",
    "type": "registry:ui",
    "dependencies": [
      "react-resizable-panels"
    ],
    "files": [
      null
    ]
  },
  {
    "name": "radio-group",
    "type": "registry:ui",
    "dependencies": [
      "@radix-ui/react-radio-group",
      "lucide-react"
    ],
    "files": [
      null
    ]
  },
  {
    "name": "progress",
    "type": "registry:ui",
    "dependencies": [
      "none"
    ],
    "files": [
      null
    ]
  },
  {
    "name": "popover",
    "type": "registry:ui",
    "dependencies": [
      "@radix-ui/react-popover"
    ],
    "files": [
      null
    ]
  },
  {
    "name": "pagination",
    "type": "registry:ui",
    "dependencies": [
      "lucide-react"
    ],
    "files": [
      null
    ]
  },
  {
    "name": "navigation-menu",
    "type": "registry:ui",
    "dependencies": [
      "@radix-ui/react-navigation-menu",
      "lucide-react",
      "class-variance-authority"
    ],
    "files": [
      null
    ]
  },
  {
    "name": "menubar",
    "type": "registry:ui",
    "dependencies": [
      "@radix-ui/react-menubar",
      "lucide-react"
    ],
    "files": [
      null
    ]
  },
  {
    "name": "label",
    "type": "registry:ui",
    "dependencies": [
      "@radix-ui/react-label",
      "class-variance-authority"
    ],
    "files": [
      null
    ]
  },
  {
    "name": "kbd",
    "type": "registry:ui",
    "dependencies": [
      "none"
    ],
    "files": [
      null
    ]
  },
  {
    "name": "item",
    "type": "registry:ui",
    "dependencies": [
      "none",
      "class-variance-authority"
    ],
    "files": [
      null
    ]
  },
  {
    "name": "input",
    "type": "registry:ui",
    "dependencies": [
      "none"
    ],
    "files": [
      null
    ]
  },
  {
    "name": "input-otp",
    "type": "registry:ui",
    "dependencies": [
      "input-otp",
      "lucide-react"
    ],
    "files": [
      null
    ]
  },
  {
    "name": "input-group",
    "type": "registry:ui",
    "dependencies": [
      "none",
      "class-variance-authority"
    ],
    "files": [
      null
    ]
  },
  {
    "name": "hover-card",
    "type": "registry:ui",
    "dependencies": [
      "@radix-ui/react-hover-card"
    ],
    "files": [
      null
    ]
  },
  {
    "name": "field",
    "type": "registry:ui",
    "dependencies": [
      "@radix-ui/react-label",
      "class-variance-authority"
    ],
    "files": [
      null
    ]
  },
  {
    "name": "empty",
    "type": "registry:ui",
    "dependencies": [
      "lucide-react",
      "class-variance-authority"
    ],
    "files": [
      null
    ]
  },
  {
    "name": "dropdown-menu",
    "type": "registry:ui",
    "dependencies": [
      "@radix-ui/react-dropdown-menu",
      "lucide-react"
    ],
    "files": [
      null
    ]
  },
  {
    "name": "drawer",
    "type": "registry:ui",
    "dependencies": [
      "vaul",
      "lucide-react"
    ],
    "files": [
      null
    ]
  },
  {
    "name": "dialog",
    "type": "registry:ui",
    "dependencies": [
      "@radix-ui/react-dialog",
      "lucide-react"
    ],
    "files": [
      null
    ]
  },
  {
    "name": "context-menu",
    "type": "registry:ui",
    "dependencies": [
      "@radix-ui/react-context-menu",
      "lucide-react"
    ],
    "files": [
      null
    ]
  },
  {
    "name": "command",
    "type": "registry:ui",
    "dependencies": [
      "cmdk",
      "lucide-react"
    ],
    "files": [
      null
    ]
  },
  {
    "name": "collapsible",
    "type": "registry:ui",
    "dependencies": [
      "@radix-ui/react-collapsible"
    ],
    "files": [
      null
    ]
  },
  {
    "name": "checkbox",
    "type": "registry:ui",
    "dependencies": [
      "@radix-ui/react-checkbox",
      "lucide-react"
    ],
    "files": [
      null
    ]
  },
  {
    "name": "chart",
    "type": "registry:ui",
    "dependencies": [
      "recharts",
      "lucide-react"
    ],
    "files": [
      null
    ]
  },
  {
    "name": "carousel",
    "type": "registry:ui",
    "dependencies": [
      "embla-carousel-react",
      "lucide-react"
    ],
    "files": [
      null
    ]
  },
  {
    "name": "card",
    "type": "registry:ui",
    "dependencies": [
      "none"
    ],
    "files": [
      null
    ]
  },
  {
    "name": "calendar",
    "type": "registry:ui",
    "dependencies": [
      "react-day-picker",
      "date-fns",
      "lucide-react"
    ],
    "files": [
      null
    ]
  },
  {
    "name": "button",
    "type": "registry:ui",
    "dependencies": [
      "@radix-ui/react-slot",
      "class-variance-authority"
    ],
    "files": [
      null
    ]
  },
  {
    "name": "button-group",
    "type": "registry:ui",
    "dependencies": [
      "class-variance-authority"
    ],
    "files": [
      null
    ]
  },
  {
    "name": "breadcrumb",
    "type": "registry:ui",
    "dependencies": [
      "@radix-ui/react-slot",
      "lucide-react"
    ],
    "files": [
      null
    ]
  },
  {
    "name": "badge",
    "type": "registry:ui",
    "dependencies": [
      "class-variance-authority",
      "lucide-react",
      "radix-ui"
    ],
    "files": [
      null
    ]
  },
  {
    "name": "avatar",
    "type": "registry:ui",
    "dependencies": [
      "@radix-ui/react-avatar"
    ],
    "files": [
      null
    ]
  },
  {
    "name": "aspect-ratio",
    "type": "registry:ui",
    "dependencies": [
      "@radix-ui/react-aspect-ratio"
    ],
    "files": [
      null
    ]
  },
  {
    "name": "alert",
    "type": "registry:ui",
    "dependencies": [
      "class-variance-authority"
    ],
    "files": [
      null
    ]
  },
  {
    "name": "alert-dialog",
    "type": "registry:ui",
    "dependencies": [
      "radix-ui"
    ],
    "files": [
      null
    ]
  },
  {
    "name": "accordion",
    "type": "registry:ui",
    "dependencies": [
      "@radix-ui/react-accordion",
      "lucide-react"
    ],
    "files": [
      null
    ]
  }
]